{
  "posts": [
    {
      "id": 1,
      "title": "json-server",
      "author": "typicode"
    }
  ],
  "comments": [
    {
      "id": 1,
      "body": "some comment",
      "postId": 1
    }
  ],
  "profile": {
    "name": "typicode"
  },
  "items": [
    {
      "name": "Cap",
      "imageUrl": "https://shorturl.at/fjloT",
      "weather": "cold",
      "_id": 1
    },
    {
      "name": "Sneakers",
      "imageUrl": "https://shorturl.at/dqG27",
      "weather": "warm",
      "_id": 2
    },
    {
      "name": "Blazer",
      "imageUrl": "https://shorturl.at/iyBFP",
      "weather": "warm",
      "_id": 3
    },
    {
      "name": "Scarf",
      "imageUrl": "https://shorturl.at/zNQSZ",
      "weather": "cold",
      "_id": 4
    },
    {
      "name": "Cap",
      "imageUrl": "https://shorturl.at/gjopW",
      "weather": "cold",
      "_id": 5
    }
  ]
}